{
  "project_info": {
    "project_number": "495213812367",
    "project_id": "true-copy-approval",
    "storage_bucket": "true-copy-approval.firebasestorage.app"
  },
  "client": [
    {
      "client_info": {
        "mobilesdk_app_id": "1:495213812367:android:df39eb0b8cd4d413866efa",
        "android_client_info": {
          "package_name": "com.example.digital_certificate_app"
        }
      },
      "oauth_client": [],
      "api_key": [
        {
          "current_key": "AIzaSyCr7KQC64GY28aJje-nrMqqgNCcDS0voWw"
        }
      ],
      "services": {
        "appinvite_service": {
          "other_platform_oauth_client": []
        }
      }
    }
  ],
  "configuration_version": "1"
}